{"sections":{"section_641819672967247e1b1eb4ee":{"type":"veda-63870f93c7da843b95595216","blocks":{"b754a694-8b5b-4d39-8b4c-46e7a2baa569":{"type":"heading_login_title","settings":{"VEDA_select_5":"h2","heading_login___title":"Login","heading_login___enable":true}},"6235cb8d-cf2c-42ba-bf00-315f7c16b942":{"type":"heading_login_text","settings":{"heading_login___text":"<p>Lorem ipsum dolor sit amet, consectetur adipiscing elit.<\/p>","heading_login___enable":true}},"ac4c65fa-894c-4fd9-8cc1-d66ef0cda91c":{"type":"heading_login_divider","settings":{"heading_login___divider":"wave","heading_login___enable":true}},"7b588710-0724-43f6-96e7-89fb0efdcb3a":{"type":"heading_login_space","settings":{"heading_login___space":20,"heading_login___enable":true}},"id_05ca21ef-0b93-4fb9-aa68-644afbd12ad4":{"type":"heading_recover_title","settings":{"VEDA_select_3":"h2","heading_recover___title":"Login","heading_recover___enable":true}},"10af245c-5296-43fc-9d35-b3fa53d2484f":{"type":"heading_recover_text","settings":{"heading_recover___text":"<p>Lorem ipsum dolor sit amet, consectetur adipiscing elit.<\/p>","heading_recover___enable":true}},"486861c4-1a55-4132-b8e6-a72d89660a16":{"type":"heading_recover_divider","settings":{"VEDA_select_4":"wave","heading_recover___enable":true}},"8cf654d7-8b36-421f-9229-201bb6a5d70d":{"type":"heading_recover_space","settings":{"heading_recover___space":20,"heading_recover___enable":true}}},"block_order":["b754a694-8b5b-4d39-8b4c-46e7a2baa569","6235cb8d-cf2c-42ba-bf00-315f7c16b942","ac4c65fa-894c-4fd9-8cc1-d66ef0cda91c","7b588710-0724-43f6-96e7-89fb0efdcb3a","id_05ca21ef-0b93-4fb9-aa68-644afbd12ad4","10af245c-5296-43fc-9d35-b3fa53d2484f","486861c4-1a55-4132-b8e6-a72d89660a16","8cf654d7-8b36-421f-9229-201bb6a5d70d"],"settings":{"recover_success___test":false,"error___test":false,"VEDA_slider_1":50,"VEDA_icon_1":"<i class=\"far fa-atom\"><\/i>","VEDA_switch_1":false,"guest_button___variant":"primary","guest_button___text":"{{ \"veda.customer.login_page.guest_continue\" | t }}","VEDA_icon_2":"<i class=\"far fa-times-hexagon\"><\/i>","VEDA_switch_2":true,"VEDA_select_1":"gray","VEDA_text_1":"{{ \"veda.customer.login_page.cancel\" | t }}","VEDA_icon_3":"<i class=\"far fa-badge-check\"><\/i>","VEDA_switch_3":true,"VEDA_select_2":"dark","VEDA_text_2":"{{ \"veda.customer.login_page.submit\" | t }}","VEDA_icon_4":"<i class=\"far fa-user-alt\"><\/i>","VEDA_switch_4":true,"sign_in_button___variant":"dark","sign_in_button___text":"{{ \"veda.customer.login_page.sign_in\" | t }}","VEDA_slider_3":80,"image_section___enable":true,"VEDA_text_3":"{{ \"veda.customer.login_page.forgot_password\" | t }}","VEDA_text_4":"{{ \"veda.customer.login_page.password\" | t }}","form_login___email_label":"{{ \"veda.customer.login_page.email\" | t }}","VEDA_switch_5":false,"VEDA_slider_7":0,"VEDA_select_6":"full_width"}},"veda-641819672967247e1b1eb4ed-scripts":{"type":"veda-641819672967247e1b1eb4ed-scripts","settings":{}}},"order":["section_641819672967247e1b1eb4ee","veda-641819672967247e1b1eb4ed-scripts"]}